{
  "PLAYER_ID": 1626174,
  "PLAYER_NAME": "Christian Wood",
  "NICKNAME": "Christian",
  "TEAM_ID": 1610612765,
  "TEAM_ABBREVIATION": "DET",
  "AGE": 24.0,
  "GP": 62,
  "W": 20,
  "L": 42,
  "W_PCT": 0.323,
  "MIN": 1324.6433333333334,
  "FGM": 288,
  "FGA": 508,
  "FG_PCT": 0.567,
  "FG3M": 54,
  "FG3A": 140,
  "FG3_PCT": 0.386,
  "FTM": 180,
  "FTA": 242,
  "FT_PCT": 0.744,
  "OREB": 104,
  "DREB": 286,
  "REB": 390,
  "AST": 60,
  "TOV": 84,
  "STL": 34,
  "BLK": 54,
  "BLKA": 31,
  "PF": 98,
  "PFD": 216,
  "PTS": 810,
  "PLUS_MINUS": 68,
  "NBA_FANTASY_PTS": 1548.0,
  "DD2": 12,
  "TD3": 0,
  "WNBA_FANTASY_PTS": 1490.0,
  "GP_RANK": 123,
  "W_RANK": 250,
  "L_RANK": 503,
  "W_PCT_RANK": 424,
  "MIN_RANK": 180,
  "FGM_RANK": 103,
  "FGA_RANK": 152,
  "FG_PCT_RANK": 59,
  "FG3M_RANK": 190,
  "FG3A_RANK": 203,
  "FG3_PCT_RANK": 105,
  "FTM_RANK": 51,
  "FTA_RANK": 47,
  "FT_PCT_RANK": 301,
  "OREB_RANK": 47,
  "DREB_RANK": 65,
  "REB_RANK": 53,
  "AST_RANK": 261,
  "TOV_RANK": 123,
  "STL_RANK": 203,
  "BLK_RANK": 43,
  "BLKA_RANK": 405,
  "PF_RANK": 301,
  "PFD_RANK": 42,
  "PTS_RANK": 98,
  "PLUS_MINUS_RANK": 109,
  "NBA_FANTASY_PTS_RANK": 108,
  "DD2_RANK": 41,
  "TD3_RANK": 29,
  "WNBA_FANTASY_PTS_RANK": 108,
  "Rookie": false
}