{
  "PLAYER_ID": 1629029,
  "PLAYER_NAME": "Luka Dončić",
  "NICKNAME": "Luka",
  "TEAM_ID": 1610612742,
  "TEAM_ABBREVIATION": "DAL",
  "AGE": 21.0,
  "GP": 61,
  "W": 36,
  "L": 25,
  "W_PCT": 0.59,
  "MIN": 2047.245,
  "FGM": 581,
  "FGA": 1255,
  "FG_PCT": 0.463,
  "FG3M": 171,
  "FG3A": 541,
  "FG3_PCT": 0.316,
  "FTM": 426,
  "FTA": 562,
  "FT_PCT": 0.758,
  "OREB": 78,
  "DREB": 495,
  "REB": 573,
  "AST": 538,
  "TOV": 260,
  "STL": 62,
  "BLK": 14,
  "BLKA": 67,
  "PF": 153,
  "PFD": 456,
  "PTS": 1759,
  "PLUS_MINUS": 253,
  "NBA_FANTASY_PTS": 3221.6,
  "DD2": 39,
  "TD3": 17,
  "WNBA_FANTASY_PTS": 3193.0,
  "GP_RANK": 140,
  "W_RANK": 99,
  "L_RANK": 307,
  "W_PCT_RANK": 168,
  "MIN_RANK": 45,
  "FGM_RANK": 10,
  "FGA_RANK": 9,
  "FG_PCT_RANK": 187,
  "FG3M_RANK": 22,
  "FG3A_RANK": 7,
  "FG3_PCT_RANK": 314,
  "FTM_RANK": 7,
  "FTA_RANK": 3,
  "FT_PCT_RANK": 268,
  "OREB_RANK": 73,
  "DREB_RANK": 10,
  "REB_RANK": 16,
  "AST_RANK": 4,
  "TOV_RANK": 5,
  "STL_RANK": 66,
  "BLK_RANK": 234,
  "BLKA_RANK": 516,
  "PF_RANK": 452,
  "PFD_RANK": 4,
  "PTS_RANK": 6,
  "PLUS_MINUS_RANK": 30,
  "NBA_FANTASY_PTS_RANK": 5,
  "DD2_RANK": 10,
  "TD3_RANK": 1,
  "WNBA_FANTASY_PTS_RANK": 5,
  "Rookie": false
}