{
  "PLAYER_ID": 1627783,
  "PLAYER_NAME": "Pascal Siakam",
  "NICKNAME": "Pascal",
  "TEAM_ID": 1610612761,
  "TEAM_ABBREVIATION": "TOR",
  "AGE": 26.0,
  "GP": 60,
  "W": 46,
  "L": 14,
  "W_PCT": 0.767,
  "MIN": 2110.161666666667,
  "FGM": 500,
  "FGA": 1104,
  "FG_PCT": 0.453,
  "FG3M": 131,
  "FG3A": 365,
  "FG3_PCT": 0.359,
  "FTM": 240,
  "FTA": 303,
  "FT_PCT": 0.792,
  "OREB": 64,
  "DREB": 375,
  "REB": 439,
  "AST": 207,
  "TOV": 148,
  "STL": 61,
  "BLK": 53,
  "BLKA": 60,
  "PF": 170,
  "PFD": 232,
  "PTS": 1371,
  "PLUS_MINUS": 398,
  "NBA_FANTASY_PTS": 2402.3,
  "DD2": 12,
  "TD3": 0,
  "WNBA_FANTASY_PTS": 2376.0,
  "GP_RANK": 151,
  "W_RANK": 21,
  "L_RANK": 168,
  "W_PCT_RANK": 26,
  "MIN_RANK": 32,
  "FGM_RANK": 22,
  "FGA_RANK": 17,
  "FG_PCT_RANK": 220,
  "FG3M_RANK": 54,
  "FG3A_RANK": 48,
  "FG3_PCT_RANK": 185,
  "FTM_RANK": 31,
  "FTA_RANK": 29,
  "FT_PCT_RANK": 213,
  "OREB_RANK": 109,
  "DREB_RANK": 24,
  "REB_RANK": 37,
  "AST_RANK": 75,
  "TOV_RANK": 39,
  "STL_RANK": 71,
  "BLK_RANK": 44,
  "BLKA_RANK": 502,
  "PF_RANK": 488,
  "PFD_RANK": 38,
  "PTS_RANK": 21,
  "PLUS_MINUS_RANK": 10,
  "NBA_FANTASY_PTS_RANK": 29,
  "DD2_RANK": 41,
  "TD3_RANK": 29,
  "WNBA_FANTASY_PTS_RANK": 27,
  "Rookie": false
}