{
  "PLAYER_ID": 202335,
  "PLAYER_NAME": "Patrick Patterson",
  "NICKNAME": "Patrick",
  "TEAM_ID": 1610612746,
  "TEAM_ABBREVIATION": "LAC",
  "AGE": 31.0,
  "GP": 59,
  "W": 39,
  "L": 20,
  "W_PCT": 0.661,
  "MIN": 776.1866666666666,
  "FGM": 95,
  "FGA": 233,
  "FG_PCT": 0.408,
  "FG3M": 67,
  "FG3A": 172,
  "FG3_PCT": 0.39,
  "FTM": 35,
  "FTA": 43,
  "FT_PCT": 0.814,
  "OREB": 35,
  "DREB": 116,
  "REB": 151,
  "AST": 41,
  "TOV": 21,
  "STL": 7,
  "BLK": 3,
  "BLKA": 5,
  "PF": 54,
  "PFD": 41,
  "PTS": 292,
  "PLUS_MINUS": 47,
  "NBA_FANTASY_PTS": 543.7,
  "DD2": 1,
  "TD3": 0,
  "WNBA_FANTASY_PTS": 571.0,
  "GP_RANK": 162,
  "W_RANK": 74,
  "L_RANK": 242,
  "W_PCT_RANK": 87,
  "MIN_RANK": 296,
  "FGM_RANK": 300,
  "FGA_RANK": 294,
  "FG_PCT_RANK": 379,
  "FG3M_RANK": 151,
  "FG3A_RANK": 166,
  "FG3_PCT_RANK": 91,
  "FTM_RANK": 287,
  "FTA_RANK": 305,
  "FT_PCT_RANK": 168,
  "OREB_RANK": 203,
  "DREB_RANK": 254,
  "REB_RANK": 249,
  "AST_RANK": 329,
  "TOV_RANK": 351,
  "STL_RANK": 397,
  "BLK_RANK": 406,
  "BLKA_RANK": 142,
  "PF_RANK": 202,
  "PFD_RANK": 315,
  "PTS_RANK": 283,
  "PLUS_MINUS_RANK": 130,
  "NBA_FANTASY_PTS_RANK": 307,
  "DD2_RANK": 187,
  "TD3_RANK": 29,
  "WNBA_FANTASY_PTS_RANK": 296,
  "Rookie": false
}