{
  "PLAYER_ID": 2760,
  "PLAYER_NAME": "Anderson Varejao",
  "NICKNAME": "Anderson",
  "TEAM_ID": 1610612739,
  "TEAM_ABBREVIATION": "CLE",
  "AGE": 25.0,
  "GP": 48,
  "W": 28,
  "L": 20,
  "W_PCT": 0.583,
  "MIN": 1319.4466666666667,
  "FGM": 136,
  "FGA": 295,
  "FG_PCT": 0.461,
  "FG3M": 0,
  "FG3A": 2,
  "FG3_PCT": 0.0,
  "FTM": 49,
  "FTA": 82,
  "FT_PCT": 0.598,
  "OREB": 134,
  "DREB": 265,
  "REB": 399,
  "AST": 53,
  "TOV": 59,
  "STL": 37,
  "BLK": 26,
  "BLKA": 25,
  "PF": 134,
  "PFD": 114,
  "PTS": 321,
  "PLUS_MINUS": 75,
  "NBA_FANTASY_PTS": 1009.3,
  "DD2": 6,
  "TD3": 0,
  "WNBA_FANTASY_PTS": 899.0,
  "GP_RANK": 300,
  "W_RANK": 214,
  "L_RANK": 140,
  "W_PCT_RANK": 156,
  "MIN_RANK": 225,
  "FGM_RANK": 248,
  "FGA_RANK": 254,
  "FG_PCT_RANK": 166,
  "FG3M_RANK": 303,
  "FG3A_RANK": 325,
  "FG3_PCT_RANK": 303,
  "FTM_RANK": 252,
  "FTA_RANK": 232,
  "FT_PCT_RANK": 365,
  "OREB_RANK": 55,
  "DREB_RANK": 99,
  "REB_RANK": 81,
  "AST_RANK": 262,
  "TOV_RANK": 223,
  "STL_RANK": 196,
  "BLK_RANK": 139,
  "BLKA_RANK": 255,
  "PF_RANK": 269,
  "PFD_RANK": 177,
  "PTS_RANK": 260,
  "PLUS_MINUS_RANK": 110,
  "NBA_FANTASY_PTS_RANK": 222,
  "DD2_RANK": 83,
  "TD3_RANK": 17,
  "WNBA_FANTASY_PTS_RANK": 231,
  "Rookie": false
}