{
  "PLAYER_ID": 959,
  "PLAYER_NAME": "Steve Nash",
  "NICKNAME": "Steve",
  "TEAM_ID": 1610612756,
  "TEAM_ABBREVIATION": "PHX",
  "AGE": 33.0,
  "GP": 76,
  "W": 59,
  "L": 17,
  "W_PCT": 0.776,
  "MIN": 2682.435,
  "FGM": 517,
  "FGA": 971,
  "FG_PCT": 0.532,
  "FG3M": 156,
  "FG3A": 343,
  "FG3_PCT": 0.455,
  "FTM": 222,
  "FTA": 247,
  "FT_PCT": 0.899,
  "OREB": 30,
  "DREB": 239,
  "REB": 269,
  "AST": 884,
  "TOV": 287,
  "STL": 57,
  "BLK": 6,
  "BLKA": 31,
  "PF": 117,
  "PFD": 262,
  "PTS": 1412,
  "PLUS_MINUS": 609,
  "NBA_FANTASY_PTS": 2962.8,
  "DD2": 53,
  "TD3": 0,
  "WNBA_FANTASY_PTS": 2847.0,
  "GP_RANK": 106,
  "W_RANK": 9,
  "L_RANK": 109,
  "W_PCT_RANK": 26,
  "MIN_RANK": 37,
  "FGM_RANK": 25,
  "FGA_RANK": 50,
  "FG_PCT_RANK": 52,
  "FG3M_RANK": 11,
  "FG3A_RANK": 23,
  "FG3_PCT_RANK": 16,
  "FTM_RANK": 65,
  "FTA_RANK": 82,
  "FT_PCT_RANK": 23,
  "OREB_RANK": 266,
  "DREB_RANK": 113,
  "REB_RANK": 137,
  "AST_RANK": 1,
  "TOV_RANK": 3,
  "STL_RANK": 116,
  "BLK_RANK": 298,
  "BLKA_RANK": 310,
  "PF_RANK": 216,
  "PFD_RANK": 54,
  "PTS_RANK": 27,
  "PLUS_MINUS_RANK": 3,
  "NBA_FANTASY_PTS_RANK": 16,
  "DD2_RANK": 3,
  "TD3_RANK": 17,
  "WNBA_FANTASY_PTS_RANK": 14,
  "Rookie": false
}