{
  "PLAYER_ID": 1630173,
  "PLAYER_NAME": "Precious Achiuwa",
  "NICKNAME": "Precious",
  "TEAM_ID": 1610612752,
  "TEAM_ABBREVIATION": "NYK",
  "AGE": 24.0,
  "GP": 74,
  "W": 40,
  "L": 34,
  "W_PCT": 0.541,
  "MIN": 1623.7533333333333,
  "FGM": 235,
  "FGA": 469,
  "FG_PCT": 0.501,
  "FG3M": 26,
  "FG3A": 97,
  "FG3_PCT": 0.268,
  "FTM": 69,
  "FTA": 112,
  "FT_PCT": 0.616,
  "OREB": 191,
  "DREB": 296,
  "REB": 487,
  "AST": 97,
  "TOV": 83,
  "STL": 46,
  "BLK": 68,
  "BLKA": 39,
  "PF": 143,
  "PFD": 84,
  "PTS": 565,
  "PLUS_MINUS": -47,
  "NBA_FANTASY_PTS": 1553.9,
  "DD2": 9,
  "TD3": 0,
  "WNBA_FANTASY_PTS": 1403.0,
  "GP_RANK": 87,
  "W_RANK": 110,
  "L_RANK": 446,
  "W_PCT_RANK": 275,
  "MIN_RANK": 171,
  "FGM_RANK": 179,
  "FGA_RANK": 190,
  "FG_PCT_RANK": 137,
  "FG3M_RANK": 296,
  "FG3A_RANK": 271,
  "FG3_PCT_RANK": 424,
  "FTM_RANK": 196,
  "FTA_RANK": 162,
  "FT_PCT_RANK": 461,
  "OREB_RANK": 17,
  "DREB_RANK": 72,
  "REB_RANK": 43,
  "AST_RANK": 228,
  "TOV_RANK": 149,
  "STL_RANK": 168,
  "BLK_RANK": 32,
  "BLKA_RANK": 446,
  "PF_RANK": 458,
  "PFD_RANK": 194,
  "PTS_RANK": 193,
  "PLUS_MINUS_RANK": 388,
  "NBA_FANTASY_PTS_RANK": 154,
  "DD2_RANK": 64,
  "TD3_RANK": 38,
  "WNBA_FANTASY_PTS_RANK": 165,
  "Rookie": false
}