{
  "PLAYER_ID": 202332,
  "PLAYER_NAME": "Cole Aldrich",
  "NICKNAME": "Cole",
  "TEAM_ID": 1610612758,
  "TEAM_ABBREVIATION": "SAC",
  "AGE": 24.0,
  "GP": 45,
  "W": 20,
  "L": 25,
  "W_PCT": 0.444,
  "MIN": 387.74,
  "FGM": 44,
  "FGA": 80,
  "FG_PCT": 0.55,
  "FG3M": 0,
  "FG3A": 0,
  "FG3_PCT": 0.0,
  "FTM": 12,
  "FTA": 20,
  "FT_PCT": 0.6,
  "OREB": 30,
  "DREB": 90,
  "REB": 120,
  "AST": 9,
  "TOV": 23,
  "STL": 5,
  "BLK": 23,
  "BLKA": 8,
  "PF": 60,
  "PFD": 18,
  "PTS": 100,
  "PLUS_MINUS": 9,
  "NBA_FANTASY_PTS": 318.5,
  "DD2": 2,
  "TD3": 0,
  "WNBA_FANTASY_PTS": 285.0,
  "GP_RANK": 323,
  "W_RANK": 298,
  "L_RANK": 203,
  "W_PCT_RANK": 281,
  "MIN_RANK": 367,
  "FGM_RANK": 369,
  "FGA_RANK": 388,
  "FG_PCT_RANK": 33,
  "FG3M_RANK": 333,
  "FG3A_RANK": 406,
  "FG3_PCT_RANK": 333,
  "FTM_RANK": 370,
  "FTA_RANK": 374,
  "FT_PCT_RANK": 368,
  "OREB_RANK": 264,
  "DREB_RANK": 289,
  "REB_RANK": 291,
  "AST_RANK": 403,
  "TOV_RANK": 345,
  "STL_RANK": 406,
  "BLK_RANK": 176,
  "BLKA_RANK": 117,
  "PF_RANK": 149,
  "PFD_RANK": 381,
  "PTS_RANK": 378,
  "PLUS_MINUS_RANK": 155,
  "NBA_FANTASY_PTS_RANK": 357,
  "DD2_RANK": 145,
  "TD3_RANK": 27,
  "WNBA_FANTASY_PTS_RANK": 361,
  "Rookie": false
}