{
  "PLAYER_ID": 2091,
  "PLAYER_NAME": "Daniel Santiago",
  "NICKNAME": "Daniel",
  "TEAM_ID": 1610612756,
  "TEAM_ABBREVIATION": "PHX",
  "AGE": 26.0,
  "GP": 3,
  "W": 0,
  "L": 3,
  "W_PCT": 0.0,
  "MIN": 24.316666666666666,
  "FGM": 4,
  "FGA": 8,
  "FG_PCT": 0.5,
  "FG3M": 0,
  "FG3A": 0,
  "FG3_PCT": 0.0,
  "FTM": 0,
  "FTA": 0,
  "FT_PCT": 0.0,
  "OREB": 0,
  "DREB": 7,
  "REB": 7,
  "AST": 2,
  "TOV": 2,
  "STL": 0,
  "BLK": 1,
  "BLKA": 1,
  "PF": 4,
  "PFD": 0,
  "PTS": 8,
  "PLUS_MINUS": -6,
  "NBA_FANTASY_PTS": 20.4,
  "DD2": 0,
  "TD3": 0,
  "WNBA_FANTASY_PTS": 19.0,
  "GP_RANK": 429,
  "W_RANK": 433,
  "L_RANK": 13,
  "W_PCT_RANK": 433,
  "MIN_RANK": 432,
  "FGM_RANK": 421,
  "FGA_RANK": 429,
  "FG_PCT_RANK": 52,
  "FG3M_RANK": 288,
  "FG3A_RANK": 361,
  "FG3_PCT_RANK": 288,
  "FTM_RANK": 429,
  "FTA_RANK": 432,
  "FT_PCT_RANK": 429,
  "OREB_RANK": 425,
  "DREB_RANK": 409,
  "REB_RANK": 417,
  "AST_RANK": 420,
  "TOV_RANK": 419,
  "STL_RANK": 420,
  "BLK_RANK": 381,
  "BLKA_RANK": 16,
  "PF_RANK": 14,
  "PFD_RANK": 153,
  "PTS_RANK": 424,
  "PLUS_MINUS_RANK": 196,
  "NBA_FANTASY_PTS_RANK": 426,
  "DD2_RANK": 225,
  "TD3_RANK": 18,
  "WNBA_FANTASY_PTS_RANK": 427,
  "Rookie": false
}