{
  "PLAYER_ID": 1901,
  "PLAYER_NAME": "Dion Glover",
  "NICKNAME": "Dion",
  "TEAM_ID": 1610612737,
  "TEAM_ABBREVIATION": "ATL",
  "AGE": 23.0,
  "GP": 55,
  "W": 20,
  "L": 35,
  "W_PCT": 0.364,
  "MIN": 1156.1816666666666,
  "FGM": 192,
  "FGA": 456,
  "FG_PCT": 0.421,
  "FG3M": 30,
  "FG3A": 91,
  "FG3_PCT": 0.33,
  "FTM": 78,
  "FTA": 103,
  "FT_PCT": 0.757,
  "OREB": 36,
  "DREB": 133,
  "REB": 169,
  "AST": 84,
  "TOV": 76,
  "STL": 45,
  "BLK": 14,
  "BLKA": 41,
  "PF": 89,
  "PFD": 0,
  "PTS": 492,
  "PLUS_MINUS": -255,
  "NBA_FANTASY_PTS": 921.8,
  "DD2": 1,
  "TD3": 0,
  "WNBA_FANTASY_PTS": 893.0,
  "GP_RANK": 261,
  "W_RANK": 281,
  "L_RANK": 299,
  "W_PCT_RANK": 330,
  "MIN_RANK": 230,
  "FGM_RANK": 178,
  "FGA_RANK": 172,
  "FG_PCT_RANK": 260,
  "FG3M_RANK": 131,
  "FG3A_RANK": 132,
  "FG3_PCT_RANK": 151,
  "FTM_RANK": 197,
  "FTA_RANK": 200,
  "FT_PCT_RANK": 188,
  "OREB_RANK": 247,
  "DREB_RANK": 232,
  "REB_RANK": 238,
  "AST_RANK": 197,
  "TOV_RANK": 177,
  "STL_RANK": 176,
  "BLK_RANK": 208,
  "BLKA_RANK": 319,
  "PF_RANK": 172,
  "PFD_RANK": 153,
  "PTS_RANK": 184,
  "PLUS_MINUS_RANK": 416,
  "NBA_FANTASY_PTS_RANK": 228,
  "DD2_RANK": 176,
  "TD3_RANK": 18,
  "WNBA_FANTASY_PTS_RANK": 215,
  "Rookie": false
}