{
  "PLAYER_ID": 2731,
  "PLAYER_NAME": "Emeka Okafor",
  "NICKNAME": "Emeka",
  "TEAM_ID": 1610612740,
  "TEAM_ABBREVIATION": "NOP",
  "AGE": 35.0,
  "GP": 26,
  "W": 16,
  "L": 10,
  "W_PCT": 0.615,
  "MIN": 353.235,
  "FGM": 48,
  "FGA": 95,
  "FG_PCT": 0.505,
  "FG3M": 0,
  "FG3A": 0,
  "FG3_PCT": 0.0,
  "FTM": 18,
  "FTA": 22,
  "FT_PCT": 0.818,
  "OREB": 47,
  "DREB": 73,
  "REB": 120,
  "AST": 8,
  "TOV": 13,
  "STL": 8,
  "BLK": 25,
  "BLKA": 11,
  "PF": 30,
  "PFD": 21,
  "PTS": 114,
  "PLUS_MINUS": 0,
  "NBA_FANTASY_PTS": 356.0,
  "DD2": 0,
  "TD3": 0,
  "WNBA_FANTASY_PTS": 308.0,
  "GP_RANK": 381,
  "W_RANK": 338,
  "L_RANK": 118,
  "W_PCT_RANK": 117,
  "MIN_RANK": 381,
  "FGM_RANK": 383,
  "FGA_RANK": 390,
  "FG_PCT_RANK": 105,
  "FG3M_RANK": 445,
  "FG3A_RANK": 492,
  "FG3_PCT_RANK": 445,
  "FTM_RANK": 374,
  "FTA_RANK": 379,
  "FT_PCT_RANK": 149,
  "OREB_RANK": 179,
  "DREB_RANK": 336,
  "REB_RANK": 311,
  "AST_RANK": 444,
  "TOV_RANK": 396,
  "STL_RANK": 388,
  "BLK_RANK": 162,
  "BLKA_RANK": 215,
  "PF_RANK": 150,
  "PFD_RANK": 382,
  "PTS_RANK": 387,
  "PLUS_MINUS_RANK": 234,
  "NBA_FANTASY_PTS_RANK": 365,
  "DD2_RANK": 228,
  "TD3_RANK": 32,
  "WNBA_FANTASY_PTS_RANK": 376,
  "Rookie": false
}