{
  "PLAYER_ID": 1627826,
  "PLAYER_NAME": "Ivica Zubac",
  "NICKNAME": "Ivica",
  "TEAM_ID": 1610612747,
  "TEAM_ABBREVIATION": "LAL",
  "AGE": 21.0,
  "GP": 43,
  "W": 19,
  "L": 24,
  "W_PCT": 0.442,
  "MIN": 409.82166666666666,
  "FGM": 61,
  "FGA": 122,
  "FG_PCT": 0.5,
  "FG3M": 0,
  "FG3A": 1,
  "FG3_PCT": 0.0,
  "FTM": 39,
  "FTA": 51,
  "FT_PCT": 0.765,
  "OREB": 45,
  "DREB": 78,
  "REB": 123,
  "AST": 25,
  "TOV": 26,
  "STL": 8,
  "BLK": 15,
  "BLKA": 12,
  "PF": 47,
  "PFD": 46,
  "PTS": 161,
  "PLUS_MINUS": 42,
  "NBA_FANTASY_PTS": 389.1,
  "DD2": 1,
  "TD3": 0,
  "WNBA_FANTASY_PTS": 355.0,
  "GP_RANK": 327,
  "W_RANK": 311,
  "L_RANK": 264,
  "W_PCT_RANK": 333,
  "MIN_RANK": 370,
  "FGM_RANK": 358,
  "FGA_RANK": 370,
  "FG_PCT_RANK": 114,
  "FG3M_RANK": 445,
  "FG3A_RANK": 470,
  "FG3_PCT_RANK": 445,
  "FTM_RANK": 285,
  "FTA_RANK": 295,
  "FT_PCT_RANK": 251,
  "OREB_RANK": 184,
  "DREB_RANK": 327,
  "REB_RANK": 308,
  "AST_RANK": 367,
  "TOV_RANK": 340,
  "STL_RANK": 388,
  "BLK_RANK": 240,
  "BLKA_RANK": 222,
  "PF_RANK": 189,
  "PFD_RANK": 313,
  "PTS_RANK": 360,
  "PLUS_MINUS_RANK": 134,
  "NBA_FANTASY_PTS_RANK": 352,
  "DD2_RANK": 177,
  "TD3_RANK": 32,
  "WNBA_FANTASY_PTS_RANK": 357,
  "Rookie": false
}