{
  "PLAYER_ID": 203917,
  "PLAYER_NAME": "Nik Stauskas",
  "NICKNAME": "Nik",
  "TEAM_ID": 1610612751,
  "TEAM_ABBREVIATION": "BKN",
  "AGE": 24.0,
  "GP": 41,
  "W": 14,
  "L": 27,
  "W_PCT": 0.341,
  "MIN": 523.3,
  "FGM": 60,
  "FGA": 154,
  "FG_PCT": 0.39,
  "FG3M": 40,
  "FG3A": 100,
  "FG3_PCT": 0.4,
  "FTM": 21,
  "FTA": 29,
  "FT_PCT": 0.724,
  "OREB": 4,
  "DREB": 60,
  "REB": 64,
  "AST": 39,
  "TOV": 26,
  "STL": 9,
  "BLK": 4,
  "BLKA": 5,
  "PF": 24,
  "PFD": 25,
  "PTS": 181,
  "PLUS_MINUS": -57,
  "NBA_FANTASY_PTS": 329.3,
  "DD2": 0,
  "TD3": 0,
  "WNBA_FANTASY_PTS": 350.0,
  "GP_RANK": 332,
  "W_RANK": 361,
  "L_RANK": 297,
  "W_PCT_RANK": 396,
  "MIN_RANK": 349,
  "FGM_RANK": 359,
  "FGA_RANK": 345,
  "FG_PCT_RANK": 421,
  "FG3M_RANK": 218,
  "FG3A_RANK": 238,
  "FG3_PCT_RANK": 77,
  "FTM_RANK": 356,
  "FTA_RANK": 354,
  "FT_PCT_RANK": 309,
  "OREB_RANK": 434,
  "DREB_RANK": 357,
  "REB_RANK": 372,
  "AST_RANK": 335,
  "TOV_RANK": 340,
  "STL_RANK": 379,
  "BLK_RANK": 369,
  "BLKA_RANK": 149,
  "PF_RANK": 135,
  "PFD_RANK": 371,
  "PTS_RANK": 347,
  "PLUS_MINUS_RANK": 382,
  "NBA_FANTASY_PTS_RANK": 373,
  "DD2_RANK": 228,
  "TD3_RANK": 32,
  "WNBA_FANTASY_PTS_RANK": 359,
  "Rookie": false
}