{
  "PLAYER_ID": 1627835,
  "PLAYER_NAME": "Paul Zipser",
  "NICKNAME": "Paul",
  "TEAM_ID": 1610612741,
  "TEAM_ABBREVIATION": "CHI",
  "AGE": 24.0,
  "GP": 54,
  "W": 17,
  "L": 37,
  "W_PCT": 0.315,
  "MIN": 824.0,
  "FGM": 81,
  "FGA": 234,
  "FG_PCT": 0.346,
  "FG3M": 37,
  "FG3A": 110,
  "FG3_PCT": 0.336,
  "FTM": 19,
  "FTA": 25,
  "FT_PCT": 0.76,
  "OREB": 13,
  "DREB": 118,
  "REB": 131,
  "AST": 46,
  "TOV": 43,
  "STL": 20,
  "BLK": 15,
  "BLKA": 14,
  "PF": 86,
  "PFD": 35,
  "PTS": 218,
  "PLUS_MINUS": -217,
  "NBA_FANTASY_PTS": 506.2,
  "DD2": 0,
  "TD3": 0,
  "WNBA_FANTASY_PTS": 502.0,
  "GP_RANK": 278,
  "W_RANK": 328,
  "L_RANK": 422,
  "W_PCT_RANK": 428,
  "MIN_RANK": 299,
  "FGM_RANK": 331,
  "FGA_RANK": 297,
  "FG_PCT_RANK": 476,
  "FG3M_RANK": 228,
  "FG3A_RANK": 228,
  "FG3_PCT_RANK": 256,
  "FTM_RANK": 369,
  "FTA_RANK": 369,
  "FT_PCT_RANK": 258,
  "OREB_RANK": 351,
  "DREB_RANK": 270,
  "REB_RANK": 292,
  "AST_RANK": 317,
  "TOV_RANK": 274,
  "STL_RANK": 317,
  "BLK_RANK": 240,
  "BLKA_RANK": 242,
  "PF_RANK": 262,
  "PFD_RANK": 348,
  "PTS_RANK": 326,
  "PLUS_MINUS_RANK": 501,
  "NBA_FANTASY_PTS_RANK": 328,
  "DD2_RANK": 228,
  "TD3_RANK": 32,
  "WNBA_FANTASY_PTS_RANK": 327,
  "Rookie": false
}