{
  "PLAYER_ID": 203968,
  "PLAYER_NAME": "Jerrelle Benimon",
  "NICKNAME": "Jerrelle",
  "TEAM_ID": 1610612743,
  "TEAM_ABBREVIATION": "DEN",
  "AGE": 23.0,
  "GP": 2,
  "W": 2,
  "L": 0,
  "W_PCT": 1.0,
  "MIN": 2.723333333333333,
  "FGM": 0,
  "FGA": 0,
  "FG_PCT": 0.0,
  "FG3M": 0,
  "FG3A": 0,
  "FG3_PCT": 0.0,
  "FTM": 0,
  "FTA": 0,
  "FT_PCT": 0.0,
  "OREB": 1,
  "DREB": 2,
  "REB": 3,
  "AST": 0,
  "TOV": 1,
  "STL": 0,
  "BLK": 0,
  "BLKA": 0,
  "PF": 0,
  "PFD": 0,
  "PTS": 0,
  "PLUS_MINUS": 6,
  "NBA_FANTASY_PTS": 2.6,
  "DD2": 0,
  "TD3": 0,
  "WNBA_FANTASY_PTS": 3.0,
  "GP_RANK": 484,
  "W_RANK": 463,
  "L_RANK": 1,
  "W_PCT_RANK": 1,
  "MIN_RANK": 489,
  "FGM_RANK": 486,
  "FGA_RANK": 491,
  "FG_PCT_RANK": 486,
  "FG3M_RANK": 381,
  "FG3A_RANK": 426,
  "FG3_PCT_RANK": 381,
  "FTM_RANK": 474,
  "FTA_RANK": 476,
  "FT_PCT_RANK": 474,
  "OREB_RANK": 460,
  "DREB_RANK": 471,
  "REB_RANK": 472,
  "AST_RANK": 485,
  "TOV_RANK": 476,
  "STL_RANK": 477,
  "BLK_RANK": 442,
  "BLKA_RANK": 1,
  "PF_RANK": 1,
  "PFD_RANK": 481,
  "PTS_RANK": 487,
  "PLUS_MINUS_RANK": 185,
  "NBA_FANTASY_PTS_RANK": 490,
  "DD2_RANK": 252,
  "TD3_RANK": 21,
  "WNBA_FANTASY_PTS_RANK": 485,
  "Rookie": true
}