{
  "PLAYER_ID": 203482,
  "PLAYER_NAME": "Kelly Olynyk",
  "NICKNAME": "Kelly",
  "TEAM_ID": 1610612738,
  "TEAM_ABBREVIATION": "BOS",
  "AGE": 24.0,
  "GP": 64,
  "W": 31,
  "L": 33,
  "W_PCT": 0.484,
  "MIN": 1423.4466666666667,
  "FGM": 251,
  "FGA": 528,
  "FG_PCT": 0.475,
  "FG3M": 61,
  "FG3A": 175,
  "FG3_PCT": 0.349,
  "FTM": 93,
  "FTA": 136,
  "FT_PCT": 0.684,
  "OREB": 92,
  "DREB": 211,
  "REB": 303,
  "AST": 109,
  "TOV": 98,
  "STL": 64,
  "BLK": 39,
  "BLKA": 31,
  "PF": 213,
  "PFD": 142,
  "PTS": 656,
  "PLUS_MINUS": 228,
  "NBA_FANTASY_PTS": 1394.1,
  "DD2": 3,
  "TD3": 0,
  "WNBA_FANTASY_PTS": 1335.0,
  "GP_RANK": 212,
  "W_RANK": 203,
  "L_RANK": 328,
  "W_PCT_RANK": 251,
  "MIN_RANK": 203,
  "FGM_RANK": 154,
  "FGA_RANK": 161,
  "FG_PCT_RANK": 125,
  "FG3M_RANK": 138,
  "FG3A_RANK": 137,
  "FG3_PCT_RANK": 166,
  "FTM_RANK": 174,
  "FTA_RANK": 168,
  "FT_PCT_RANK": 329,
  "OREB_RANK": 102,
  "DREB_RANK": 141,
  "REB_RANK": 129,
  "AST_RANK": 169,
  "TOV_RANK": 129,
  "STL_RANK": 94,
  "BLK_RANK": 91,
  "BLKA_RANK": 339,
  "PF_RANK": 473,
  "PFD_RANK": 126,
  "PTS_RANK": 156,
  "PLUS_MINUS_RANK": 44,
  "NBA_FANTASY_PTS_RANK": 153,
  "DD2_RANK": 122,
  "TD3_RANK": 21,
  "WNBA_FANTASY_PTS_RANK": 153,
  "Rookie": false
}