{
  "PLAYER_ID": 101155,
  "PLAYER_NAME": "Ryan Gomes",
  "NICKNAME": "Ryan",
  "TEAM_ID": 1610612746,
  "TEAM_ABBREVIATION": "LAC",
  "AGE": 29.0,
  "GP": 32,
  "W": 20,
  "L": 12,
  "W_PCT": 0.625,
  "MIN": 424.73333333333335,
  "FGM": 31,
  "FGA": 95,
  "FG_PCT": 0.326,
  "FG3M": 4,
  "FG3A": 29,
  "FG3_PCT": 0.138,
  "FTM": 8,
  "FTA": 11,
  "FT_PCT": 0.727,
  "OREB": 14,
  "DREB": 47,
  "REB": 61,
  "AST": 12,
  "TOV": 15,
  "STL": 16,
  "BLK": 0,
  "BLKA": 1,
  "PF": 34,
  "PFD": 11,
  "PTS": 74,
  "PLUS_MINUS": -65,
  "NBA_FANTASY_PTS": 198.2,
  "DD2": 0,
  "TD3": 0,
  "WNBA_FANTASY_PTS": 183.0,
  "GP_RANK": 336,
  "W_RANK": 251,
  "L_RANK": 101,
  "W_PCT_RANK": 102,
  "MIN_RANK": 347,
  "FGM_RANK": 373,
  "FGA_RANK": 361,
  "FG_PCT_RANK": 441,
  "FG3M_RANK": 260,
  "FG3A_RANK": 242,
  "FG3_PCT_RANK": 329,
  "FTM_RANK": 385,
  "FTA_RANK": 397,
  "FT_PCT_RANK": 258,
  "OREB_RANK": 332,
  "DREB_RANK": 342,
  "REB_RANK": 344,
  "AST_RANK": 377,
  "TOV_RANK": 373,
  "STL_RANK": 309,
  "BLK_RANK": 441,
  "BLKA_RANK": 27,
  "PF_RANK": 117,
  "PFD_RANK": 397,
  "PTS_RANK": 379,
  "PLUS_MINUS_RANK": 354,
  "NBA_FANTASY_PTS_RANK": 377,
  "DD2_RANK": 203,
  "TD3_RANK": 14,
  "WNBA_FANTASY_PTS_RANK": 381,
  "Rookie": false
}