{
  "PLAYER_ID": 916,
  "PLAYER_NAME": "Corie Blount",
  "NICKNAME": "Corie",
  "TEAM_ID": 1610612761,
  "TEAM_ABBREVIATION": "TOR",
  "AGE": 35.0,
  "GP": 62,
  "W": 18,
  "L": 44,
  "W_PCT": 0.29,
  "MIN": 1042.8116666666667,
  "FGM": 115,
  "FGA": 253,
  "FG_PCT": 0.455,
  "FG3M": 0,
  "FG3A": 3,
  "FG3_PCT": 0.0,
  "FTM": 15,
  "FTA": 27,
  "FT_PCT": 0.556,
  "OREB": 98,
  "DREB": 177,
  "REB": 275,
  "AST": 55,
  "TOV": 43,
  "STL": 49,
  "BLK": 24,
  "BLKA": 9,
  "PF": 135,
  "PFD": 0,
  "PTS": 245,
  "PLUS_MINUS": -10,
  "NBA_FANTASY_PTS": 833.5,
  "DD2": 1,
  "TD3": 0,
  "WNBA_FANTASY_PTS": 721.0,
  "GP_RANK": 216,
  "W_RANK": 303,
  "L_RANK": 381,
  "W_PCT_RANK": 388,
  "MIN_RANK": 230,
  "FGM_RANK": 244,
  "FGA_RANK": 253,
  "FG_PCT_RANK": 146,
  "FG3M_RANK": 289,
  "FG3A_RANK": 286,
  "FG3_PCT_RANK": 289,
  "FTM_RANK": 349,
  "FTA_RANK": 333,
  "FT_PCT_RANK": 383,
  "OREB_RANK": 104,
  "DREB_RANK": 168,
  "REB_RANK": 144,
  "AST_RANK": 245,
  "TOV_RANK": 268,
  "STL_RANK": 171,
  "BLK_RANK": 131,
  "BLKA_RANK": 122,
  "PF_RANK": 255,
  "PFD_RANK": 79,
  "PTS_RANK": 267,
  "PLUS_MINUS_RANK": 200,
  "NBA_FANTASY_PTS_RANK": 229,
  "DD2_RANK": 178,
  "TD3_RANK": 19,
  "WNBA_FANTASY_PTS_RANK": 234,
  "Rookie": false
}