{
  "PLAYER_ID": 1630169,
  "PLAYER_NAME": "Tyrese Haliburton",
  "NICKNAME": "Tyrese",
  "TEAM_ID": 1610612754,
  "TEAM_ABBREVIATION": "IND",
  "AGE": 25.0,
  "GP": 73,
  "W": 46,
  "L": 27,
  "W_PCT": 0.63,
  "MIN": 2450.391666666667,
  "FGM": 476,
  "FGA": 1006,
  "FG_PCT": 0.473,
  "FG3M": 218,
  "FG3A": 562,
  "FG3_PCT": 0.388,
  "FTM": 189,
  "FTA": 222,
  "FT_PCT": 0.851,
  "OREB": 42,
  "DREB": 216,
  "REB": 258,
  "AST": 673,
  "TOV": 120,
  "STL": 105,
  "BLK": 49,
  "BLKA": 23,
  "PF": 92,
  "PFD": 175,
  "PTS": 1359,
  "PLUS_MINUS": 222,
  "NBA_FANTASY_PTS": 3020.1,
  "DD2": 31,
  "TD3": 0,
  "WNBA_FANTASY_PTS": 2816.0,
  "GP_RANK": 86,
  "W_RANK": 45,
  "L_RANK": 334,
  "W_PCT_RANK": 121,
  "MIN_RANK": 30,
  "FGM_RANK": 43,
  "FGA_RANK": 45,
  "FG_PCT_RANK": 200,
  "FG3M_RANK": 13,
  "FG3A_RANK": 15,
  "FG3_PCT_RANK": 118,
  "FTM_RANK": 61,
  "FTA_RANK": 70,
  "FT_PCT_RANK": 105,
  "OREB_RANK": 237,
  "DREB_RANK": 124,
  "REB_RANK": 163,
  "AST_RANK": 4,
  "TOV_RANK": 76,
  "STL_RANK": 14,
  "BLK_RANK": 64,
  "BLKA_RANK": 356,
  "PF_RANK": 321,
  "PFD_RANK": 74,
  "PTS_RANK": 38,
  "PLUS_MINUS_RANK": 64,
  "NBA_FANTASY_PTS_RANK": 16,
  "DD2_RANK": 18,
  "TD3_RANK": 44,
  "WNBA_FANTASY_PTS_RANK": 19,
  "Rookie": false
}