{
  "PLAYER_ID": 201572,
  "PLAYER_NAME": "Brook Lopez",
  "NICKNAME": "Brook",
  "TEAM_ID": 1610612749,
  "TEAM_ABBREVIATION": "MIL",
  "AGE": 34.0,
  "GP": 13,
  "W": 10,
  "L": 3,
  "W_PCT": 0.769,
  "MIN": 298.4066666666667,
  "FGM": 61,
  "FGA": 131,
  "FG_PCT": 0.466,
  "FG3M": 19,
  "FG3A": 53,
  "FG3_PCT": 0.358,
  "FTM": 20,
  "FTA": 23,
  "FT_PCT": 0.87,
  "OREB": 19,
  "DREB": 34,
  "REB": 53,
  "AST": 6,
  "TOV": 12,
  "STL": 8,
  "BLK": 15,
  "BLKA": 5,
  "PF": 34,
  "PFD": 21,
  "PTS": 161,
  "PLUS_MINUS": -7,
  "NBA_FANTASY_PTS": 290.6,
  "DD2": 0,
  "TD3": 0,
  "WNBA_FANTASY_PTS": 285.0,
  "GP_RANK": 474,
  "W_RANK": 427,
  "L_RANK": 72,
  "W_PCT_RANK": 44,
  "MIN_RANK": 427,
  "FGM_RANK": 382,
  "FGA_RANK": 390,
  "FG_PCT_RANK": 220,
  "FG3M_RANK": 327,
  "FG3A_RANK": 344,
  "FG3_PCT_RANK": 188,
  "FTM_RANK": 371,
  "FTA_RANK": 390,
  "FT_PCT_RANK": 84,
  "OREB_RANK": 358,
  "DREB_RANK": 429,
  "REB_RANK": 422,
  "AST_RANK": 490,
  "TOV_RANK": 426,
  "STL_RANK": 417,
  "BLK_RANK": 251,
  "BLKA_RANK": 179,
  "PF_RANK": 199,
  "PFD_RANK": 397,
  "PTS_RANK": 382,
  "PLUS_MINUS_RANK": 300,
  "NBA_FANTASY_PTS_RANK": 409,
  "DD2_RANK": 268,
  "TD3_RANK": 40,
  "WNBA_FANTASY_PTS_RANK": 408,
  "Rookie": false
}