{
  "PLAYER_ID": 1630179,
  "PLAYER_NAME": "Tyrell Terry",
  "NICKNAME": "Tyrell",
  "TEAM_ID": 1610612763,
  "TEAM_ABBREVIATION": "MEM",
  "AGE": 21.0,
  "GP": 2,
  "W": 2,
  "L": 0,
  "W_PCT": 1.0,
  "MIN": 3.05,
  "FGM": 1,
  "FGA": 1,
  "FG_PCT": 1.0,
  "FG3M": 0,
  "FG3A": 0,
  "FG3_PCT": 0.0,
  "FTM": 0,
  "FTA": 0,
  "FT_PCT": 0.0,
  "OREB": 0,
  "DREB": 0,
  "REB": 0,
  "AST": 0,
  "TOV": 0,
  "STL": 0,
  "BLK": 0,
  "BLKA": 0,
  "PF": 1,
  "PFD": 0,
  "PTS": 2,
  "PLUS_MINUS": -2,
  "NBA_FANTASY_PTS": 2.0,
  "DD2": 0,
  "TD3": 0,
  "WNBA_FANTASY_PTS": 2.0,
  "GP_RANK": 566,
  "W_RANK": 512,
  "L_RANK": 1,
  "W_PCT_RANK": 1,
  "MIN_RANK": 593,
  "FGM_RANK": 561,
  "FGA_RANK": 587,
  "FG_PCT_RANK": 1,
  "FG3M_RANK": 514,
  "FG3A_RANK": 562,
  "FG3_PCT_RANK": 514,
  "FTM_RANK": 543,
  "FTA_RANK": 547,
  "FT_PCT_RANK": 543,
  "OREB_RANK": 557,
  "DREB_RANK": 583,
  "REB_RANK": 586,
  "AST_RANK": 569,
  "TOV_RANK": 566,
  "STL_RANK": 554,
  "BLK_RANK": 520,
  "BLKA_RANK": 1,
  "PF_RANK": 23,
  "PFD_RANK": 564,
  "PTS_RANK": 570,
  "PLUS_MINUS_RANK": 272,
  "NBA_FANTASY_PTS_RANK": 589,
  "DD2_RANK": 268,
  "TD3_RANK": 40,
  "WNBA_FANTASY_PTS_RANK": 588,
  "Rookie": false
}