{
  "PLAYER_ID": 1628963,
  "PLAYER_NAME": "Marvin Bagley III",
  "NICKNAME": "Marvin",
  "TEAM_ID": 1610612758,
  "TEAM_ABBREVIATION": "SAC",
  "AGE": 22.0,
  "GP": 43,
  "W": 20,
  "L": 23,
  "W_PCT": 0.465,
  "MIN": 1111.8283333333334,
  "FGM": 247,
  "FGA": 490,
  "FG_PCT": 0.504,
  "FG3M": 37,
  "FG3A": 108,
  "FG3_PCT": 0.343,
  "FTM": 77,
  "FTA": 134,
  "FT_PCT": 0.575,
  "OREB": 106,
  "DREB": 212,
  "REB": 318,
  "AST": 43,
  "TOV": 59,
  "STL": 21,
  "BLK": 21,
  "BLKA": 42,
  "PF": 100,
  "PFD": 116,
  "PTS": 608,
  "PLUS_MINUS": -87,
  "NBA_FANTASY_PTS": 1121.1,
  "DD2": 11,
  "TD3": 0,
  "WNBA_FANTASY_PTS": 1090.0,
  "GP_RANK": 297,
  "W_RANK": 279,
  "L_RANK": 297,
  "W_PCT_RANK": 304,
  "MIN_RANK": 225,
  "FGM_RANK": 144,
  "FGA_RANK": 158,
  "FG_PCT_RANK": 115,
  "FG3M_RANK": 248,
  "FG3A_RANK": 251,
  "FG3_PCT_RANK": 252,
  "FTM_RANK": 160,
  "FTA_RANK": 117,
  "FT_PCT_RANK": 471,
  "OREB_RANK": 46,
  "DREB_RANK": 121,
  "REB_RANK": 89,
  "AST_RANK": 329,
  "TOV_RANK": 187,
  "STL_RANK": 301,
  "BLK_RANK": 168,
  "BLKA_RANK": 472,
  "PF_RANK": 349,
  "PFD_RANK": 125,
  "PTS_RANK": 160,
  "PLUS_MINUS_RANK": 432,
  "NBA_FANTASY_PTS_RANK": 190,
  "DD2_RANK": 51,
  "TD3_RANK": 29,
  "WNBA_FANTASY_PTS_RANK": 186,
  "Rookie": false
}