{
  "PLAYER_ID": 203082,
  "PLAYER_NAME": "Terrence Ross",
  "NICKNAME": "Terrence",
  "TEAM_ID": 1610612753,
  "TEAM_ABBREVIATION": "ORL",
  "AGE": 30.0,
  "GP": 46,
  "W": 16,
  "L": 30,
  "W_PCT": 0.348,
  "MIN": 1346.4866666666667,
  "FGM": 254,
  "FGA": 616,
  "FG_PCT": 0.412,
  "FG3M": 89,
  "FG3A": 264,
  "FG3_PCT": 0.337,
  "FTM": 120,
  "FTA": 138,
  "FT_PCT": 0.87,
  "OREB": 15,
  "DREB": 143,
  "REB": 158,
  "AST": 108,
  "TOV": 74,
  "STL": 47,
  "BLK": 21,
  "BLKA": 28,
  "PF": 88,
  "PFD": 103,
  "PTS": 717,
  "PLUS_MINUS": -235,
  "NBA_FANTASY_PTS": 1198.6,
  "DD2": 0,
  "TD3": 0,
  "WNBA_FANTASY_PTS": 1208.0,
  "GP_RANK": 268,
  "W_RANK": 331,
  "L_RANK": 413,
  "W_PCT_RANK": 428,
  "MIN_RANK": 171,
  "FGM_RANK": 135,
  "FGA_RANK": 107,
  "FG_PCT_RANK": 377,
  "FG3M_RANK": 123,
  "FG3A_RANK": 108,
  "FG3_PCT_RANK": 272,
  "FTM_RANK": 99,
  "FTA_RANK": 109,
  "FT_PCT_RANK": 83,
  "OREB_RANK": 355,
  "DREB_RANK": 220,
  "REB_RANK": 249,
  "AST_RANK": 164,
  "TOV_RANK": 140,
  "STL_RANK": 125,
  "BLK_RANK": 168,
  "BLKA_RANK": 399,
  "PF_RANK": 306,
  "PFD_RANK": 144,
  "PTS_RANK": 126,
  "PLUS_MINUS_RANK": 520,
  "NBA_FANTASY_PTS_RANK": 169,
  "DD2_RANK": 245,
  "TD3_RANK": 29,
  "WNBA_FANTASY_PTS_RANK": 163,
  "Rookie": false
}