{
  "PLAYER_ID": 1711,
  "PLAYER_NAME": "Raef LaFrentz",
  "NICKNAME": "Raef",
  "TEAM_ID": 1610612742,
  "TEAM_ABBREVIATION": "DAL",
  "AGE": 27.0,
  "GP": 69,
  "W": 48,
  "L": 21,
  "W_PCT": 0.696,
  "MIN": 1610.0416666666667,
  "FGM": 266,
  "FGA": 514,
  "FG_PCT": 0.518,
  "FG3M": 47,
  "FG3A": 116,
  "FG3_PCT": 0.405,
  "FTM": 60,
  "FTA": 88,
  "FT_PCT": 0.682,
  "OREB": 125,
  "DREB": 205,
  "REB": 330,
  "AST": 54,
  "TOV": 46,
  "STL": 35,
  "BLK": 91,
  "BLKA": 43,
  "PF": 264,
  "PFD": 1,
  "PTS": 639,
  "PLUS_MINUS": 222,
  "NBA_FANTASY_PTS": 1448.0,
  "DD2": 5,
  "TD3": 0,
  "WNBA_FANTASY_PTS": 1322.0,
  "GP_RANK": 187,
  "W_RANK": 36,
  "L_RANK": 134,
  "W_PCT_RANK": 44,
  "MIN_RANK": 173,
  "FGM_RANK": 123,
  "FGA_RANK": 153,
  "FG_PCT_RANK": 30,
  "FG3M_RANK": 105,
  "FG3A_RANK": 121,
  "FG3_PCT_RANK": 32,
  "FTM_RANK": 225,
  "FTA_RANK": 219,
  "FT_PCT_RANK": 292,
  "OREB_RANK": 78,
  "DREB_RANK": 143,
  "REB_RANK": 119,
  "AST_RANK": 244,
  "TOV_RANK": 261,
  "STL_RANK": 215,
  "BLK_RANK": 27,
  "BLKA_RANK": 327,
  "PF_RANK": 417,
  "PFD_RANK": 36,
  "PTS_RANK": 141,
  "PLUS_MINUS_RANK": 36,
  "NBA_FANTASY_PTS_RANK": 143,
  "DD2_RANK": 91,
  "TD3_RANK": 26,
  "WNBA_FANTASY_PTS_RANK": 149,
  "Rookie": false
}