{
  "PLAYER_ID": 693,
  "PLAYER_NAME": "Joe Smith",
  "NICKNAME": "Joe",
  "TEAM_ID": 1610612749,
  "TEAM_ABBREVIATION": "MIL",
  "AGE": 29.0,
  "GP": 74,
  "W": 28,
  "L": 46,
  "W_PCT": 0.378,
  "MIN": 2270.8683333333333,
  "FGM": 319,
  "FGA": 621,
  "FG_PCT": 0.514,
  "FG3M": 0,
  "FG3A": 1,
  "FG3_PCT": 0.0,
  "FTM": 175,
  "FTA": 228,
  "FT_PCT": 0.768,
  "OREB": 179,
  "DREB": 362,
  "REB": 541,
  "AST": 67,
  "TOV": 79,
  "STL": 43,
  "BLK": 38,
  "BLKA": 46,
  "PF": 222,
  "PFD": 1,
  "PTS": 813,
  "PLUS_MINUS": -71,
  "NBA_FANTASY_PTS": 1726.7,
  "DD2": 14,
  "TD3": 0,
  "WNBA_FANTASY_PTS": 1583.0,
  "GP_RANK": 128,
  "W_RANK": 222,
  "L_RANK": 413,
  "W_PCT_RANK": 346,
  "MIN_RANK": 89,
  "FGM_RANK": 101,
  "FGA_RANK": 125,
  "FG_PCT_RANK": 48,
  "FG3M_RANK": 301,
  "FG3A_RANK": 351,
  "FG3_PCT_RANK": 301,
  "FTM_RANK": 92,
  "FTA_RANK": 90,
  "FT_PCT_RANK": 192,
  "OREB_RANK": 34,
  "DREB_RANK": 40,
  "REB_RANK": 35,
  "AST_RANK": 231,
  "TOV_RANK": 183,
  "STL_RANK": 176,
  "BLK_RANK": 94,
  "BLKA_RANK": 381,
  "PF_RANK": 418,
  "PFD_RANK": 10,
  "PTS_RANK": 108,
  "PLUS_MINUS_RANK": 339,
  "NBA_FANTASY_PTS_RANK": 106,
  "DD2_RANK": 51,
  "TD3_RANK": 14,
  "WNBA_FANTASY_PTS_RANK": 110,
  "Rookie": false
}