{
  "PLAYER_ID": 201971,
  "PLAYER_NAME": "DeJuan Blair",
  "NICKNAME": "DeJuan",
  "TEAM_ID": 1610612742,
  "TEAM_ABBREVIATION": "DAL",
  "AGE": 25.0,
  "GP": 78,
  "W": 46,
  "L": 32,
  "W_PCT": 0.59,
  "MIN": 1213.8233333333333,
  "FGM": 210,
  "FGA": 393,
  "FG_PCT": 0.534,
  "FG3M": 0,
  "FG3A": 2,
  "FG3_PCT": 0.0,
  "FTM": 77,
  "FTA": 121,
  "FT_PCT": 0.636,
  "OREB": 139,
  "DREB": 229,
  "REB": 368,
  "AST": 70,
  "TOV": 77,
  "STL": 60,
  "BLK": 21,
  "BLKA": 46,
  "PF": 192,
  "PFD": 96,
  "PTS": 497,
  "PLUS_MINUS": -4,
  "NBA_FANTASY_PTS": 1209.6,
  "DD2": 2,
  "TD3": 0,
  "WNBA_FANTASY_PTS": 1097.0,
  "GP_RANK": 89,
  "W_RANK": 78,
  "L_RANK": 296,
  "W_PCT_RANK": 155,
  "MIN_RANK": 230,
  "FGM_RANK": 191,
  "FGA_RANK": 215,
  "FG_PCT_RANK": 47,
  "FG3M_RANK": 349,
  "FG3A_RANK": 363,
  "FG3_PCT_RANK": 349,
  "FTM_RANK": 199,
  "FTA_RANK": 175,
  "FT_PCT_RANK": 365,
  "OREB_RANK": 50,
  "DREB_RANK": 124,
  "REB_RANK": 82,
  "AST_RANK": 233,
  "TOV_RANK": 187,
  "STL_RANK": 117,
  "BLK_RANK": 179,
  "BLKA_RANK": 406,
  "PF_RANK": 414,
  "PFD_RANK": 199,
  "PTS_RANK": 205,
  "PLUS_MINUS_RANK": 226,
  "NBA_FANTASY_PTS_RANK": 192,
  "DD2_RANK": 140,
  "TD3_RANK": 27,
  "WNBA_FANTASY_PTS_RANK": 198,
  "Rookie": false
}