{
  "PLAYER_ID": 201952,
  "PLAYER_NAME": "Jeff Teague",
  "NICKNAME": "Jeff",
  "TEAM_ID": 1610612737,
  "TEAM_ABBREVIATION": "ATL",
  "AGE": 26.0,
  "GP": 79,
  "W": 37,
  "L": 42,
  "W_PCT": 0.468,
  "MIN": 2541.9216666666666,
  "FGM": 456,
  "FGA": 1040,
  "FG_PCT": 0.438,
  "FG3M": 74,
  "FG3A": 225,
  "FG3_PCT": 0.329,
  "FTM": 318,
  "FTA": 376,
  "FT_PCT": 0.846,
  "OREB": 34,
  "DREB": 174,
  "REB": 208,
  "AST": 528,
  "TOV": 232,
  "STL": 89,
  "BLK": 17,
  "BLKA": 73,
  "PF": 158,
  "PFD": 325,
  "PTS": 1304,
  "PLUS_MINUS": 117,
  "NBA_FANTASY_PTS": 2431.6,
  "DD2": 13,
  "TD3": 0,
  "WNBA_FANTASY_PTS": 2326.0,
  "GP_RANK": 75,
  "W_RANK": 140,
  "L_RANK": 402,
  "W_PCT_RANK": 270,
  "MIN_RANK": 45,
  "FGM_RANK": 42,
  "FGA_RANK": 33,
  "FG_PCT_RANK": 236,
  "FG3M_RANK": 101,
  "FG3A_RANK": 96,
  "FG3_PCT_RANK": 212,
  "FTM_RANK": 18,
  "FTA_RANK": 23,
  "FT_PCT_RANK": 76,
  "OREB_RANK": 245,
  "DREB_RANK": 185,
  "REB_RANK": 203,
  "AST_RANK": 8,
  "TOV_RANK": 10,
  "STL_RANK": 47,
  "BLK_RANK": 208,
  "BLKA_RANK": 462,
  "PF_RANK": 360,
  "PFD_RANK": 23,
  "PTS_RANK": 30,
  "PLUS_MINUS_RANK": 97,
  "NBA_FANTASY_PTS_RANK": 43,
  "DD2_RANK": 51,
  "TD3_RANK": 27,
  "WNBA_FANTASY_PTS_RANK": 42,
  "Rookie": false
}