{
  "PLAYER_ID": 200757,
  "PLAYER_NAME": "Thabo Sefolosha",
  "NICKNAME": "Thabo",
  "TEAM_ID": 1610612760,
  "TEAM_ABBREVIATION": "OKC",
  "AGE": 30.0,
  "GP": 61,
  "W": 44,
  "L": 17,
  "W_PCT": 0.721,
  "MIN": 1584.095,
  "FGM": 141,
  "FGA": 340,
  "FG_PCT": 0.415,
  "FG3M": 48,
  "FG3A": 152,
  "FG3_PCT": 0.316,
  "FTM": 53,
  "FTA": 69,
  "FT_PCT": 0.768,
  "OREB": 50,
  "DREB": 170,
  "REB": 220,
  "AST": 94,
  "TOV": 55,
  "STL": 79,
  "BLK": 17,
  "BLKA": 18,
  "PF": 90,
  "PFD": 52,
  "PTS": 383,
  "PLUS_MINUS": 119,
  "NBA_FANTASY_PTS": 1021.0,
  "DD2": 0,
  "TD3": 0,
  "WNBA_FANTASY_PTS": 937.0,
  "GP_RANK": 239,
  "W_RANK": 93,
  "L_RANK": 136,
  "W_PCT_RANK": 39,
  "MIN_RANK": 177,
  "FGM_RANK": 247,
  "FGA_RANK": 237,
  "FG_PCT_RANK": 331,
  "FG3M_RANK": 159,
  "FG3A_RANK": 151,
  "FG3_PCT_RANK": 234,
  "FTM_RANK": 240,
  "FTA_RANK": 247,
  "FT_PCT_RANK": 208,
  "OREB_RANK": 188,
  "DREB_RANK": 192,
  "REB_RANK": 191,
  "AST_RANK": 185,
  "TOV_RANK": 248,
  "STL_RANK": 62,
  "BLK_RANK": 208,
  "BLKA_RANK": 241,
  "PF_RANK": 208,
  "PFD_RANK": 294,
  "PTS_RANK": 245,
  "PLUS_MINUS_RANK": 94,
  "NBA_FANTASY_PTS_RANK": 216,
  "DD2_RANK": 234,
  "TD3_RANK": 27,
  "WNBA_FANTASY_PTS_RANK": 222,
  "Rookie": false
}