{
  "PLAYER_ID": 200772,
  "PLAYER_NAME": "Maurice Ager",
  "NICKNAME": "Maurice",
  "TEAM_ID": 1610612751,
  "TEAM_ABBREVIATION": "NJN",
  "AGE": 25.0,
  "GP": 20,
  "W": 7,
  "L": 13,
  "W_PCT": 0.35,
  "MIN": 97.31666666666666,
  "FGM": 15,
  "FGA": 43,
  "FG_PCT": 0.349,
  "FG3M": 0,
  "FG3A": 6,
  "FG3_PCT": 0.0,
  "FTM": 4,
  "FTA": 8,
  "FT_PCT": 0.5,
  "OREB": 3,
  "DREB": 7,
  "REB": 10,
  "AST": 3,
  "TOV": 4,
  "STL": 1,
  "BLK": 2,
  "BLKA": 4,
  "PF": 17,
  "PFD": 8,
  "PTS": 34,
  "PLUS_MINUS": -14,
  "NBA_FANTASY_PTS": 55.5,
  "DD2": 0,
  "TD3": 0,
  "WNBA_FANTASY_PTS": 53.0,
  "GP_RANK": 383,
  "W_RANK": 388,
  "L_RANK": 84,
  "W_PCT_RANK": 337,
  "MIN_RANK": 404,
  "FGM_RANK": 395,
  "FGA_RANK": 393,
  "FG_PCT_RANK": 407,
  "FG3M_RANK": 304,
  "FG3A_RANK": 282,
  "FG3_PCT_RANK": 304,
  "FTM_RANK": 400,
  "FTA_RANK": 394,
  "FT_PCT_RANK": 391,
  "OREB_RANK": 410,
  "DREB_RANK": 415,
  "REB_RANK": 418,
  "AST_RANK": 400,
  "TOV_RANK": 409,
  "STL_RANK": 407,
  "BLK_RANK": 374,
  "BLKA_RANK": 62,
  "PF_RANK": 53,
  "PFD_RANK": 396,
  "PTS_RANK": 401,
  "PLUS_MINUS_RANK": 221,
  "NBA_FANTASY_PTS_RANK": 408,
  "DD2_RANK": 229,
  "TD3_RANK": 15,
  "WNBA_FANTASY_PTS_RANK": 410,
  "Rookie": false
}