{
  "PLAYER_ID": 200761,
  "PLAYER_NAME": "Shawne Williams",
  "NICKNAME": "Shawne",
  "TEAM_ID": 1610612742,
  "TEAM_ABBREVIATION": "DAL",
  "AGE": 23.0,
  "GP": 15,
  "W": 10,
  "L": 5,
  "W_PCT": 0.667,
  "MIN": 169.65833333333333,
  "FGM": 16,
  "FGA": 56,
  "FG_PCT": 0.286,
  "FG3M": 1,
  "FG3A": 17,
  "FG3_PCT": 0.059,
  "FTM": 9,
  "FTA": 11,
  "FT_PCT": 0.818,
  "OREB": 19,
  "DREB": 27,
  "REB": 46,
  "AST": 2,
  "TOV": 5,
  "STL": 2,
  "BLK": 9,
  "BLKA": 6,
  "PF": 19,
  "PFD": 10,
  "PTS": 42,
  "PLUS_MINUS": 12,
  "NBA_FANTASY_PTS": 128.2,
  "DD2": 0,
  "TD3": 0,
  "WNBA_FANTASY_PTS": 113.0,
  "GP_RANK": 398,
  "W_RANK": 366,
  "L_RANK": 34,
  "W_PCT_RANK": 71,
  "MIN_RANK": 391,
  "FGM_RANK": 392,
  "FGA_RANK": 383,
  "FG_PCT_RANK": 429,
  "FG3M_RANK": 283,
  "FG3A_RANK": 256,
  "FG3_PCT_RANK": 303,
  "FTM_RANK": 377,
  "FTA_RANK": 386,
  "FT_PCT_RANK": 124,
  "OREB_RANK": 311,
  "DREB_RANK": 369,
  "REB_RANK": 359,
  "AST_RANK": 408,
  "TOV_RANK": 404,
  "STL_RANK": 400,
  "BLK_RANK": 272,
  "BLKA_RANK": 91,
  "PF_RANK": 58,
  "PFD_RANK": 389,
  "PTS_RANK": 393,
  "PLUS_MINUS_RANK": 148,
  "NBA_FANTASY_PTS_RANK": 390,
  "DD2_RANK": 229,
  "TD3_RANK": 15,
  "WNBA_FANTASY_PTS_RANK": 392,
  "Rookie": false
}