{
  "PLAYER_ID": 2437,
  "PLAYER_NAME": "Lonny Baxter",
  "NICKNAME": "Lonny",
  "TEAM_ID": 1610612766,
  "TEAM_ABBREVIATION": "CHA",
  "AGE": 27.0,
  "GP": 41,
  "W": 13,
  "L": 28,
  "W_PCT": 0.317,
  "MIN": 400.54333333333335,
  "FGM": 45,
  "FGA": 104,
  "FG_PCT": 0.433,
  "FG3M": 0,
  "FG3A": 0,
  "FG3_PCT": 0.0,
  "FTM": 28,
  "FTA": 35,
  "FT_PCT": 0.8,
  "OREB": 45,
  "DREB": 72,
  "REB": 117,
  "AST": 4,
  "TOV": 20,
  "STL": 11,
  "BLK": 8,
  "BLKA": 15,
  "PF": 56,
  "PFD": 40,
  "PTS": 118,
  "PLUS_MINUS": 20,
  "NBA_FANTASY_PTS": 301.4,
  "DD2": 1,
  "TD3": 0,
  "WNBA_FANTASY_PTS": 277.0,
  "GP_RANK": 320,
  "W_RANK": 362,
  "L_RANK": 218,
  "W_PCT_RANK": 392,
  "MIN_RANK": 338,
  "FGM_RANK": 332,
  "FGA_RANK": 331,
  "FG_PCT_RANK": 244,
  "FG3M_RANK": 307,
  "FG3A_RANK": 371,
  "FG3_PCT_RANK": 307,
  "FTM_RANK": 312,
  "FTA_RANK": 328,
  "FT_PCT_RANK": 113,
  "OREB_RANK": 203,
  "DREB_RANK": 300,
  "REB_RANK": 286,
  "AST_RANK": 412,
  "TOV_RANK": 346,
  "STL_RANK": 335,
  "BLK_RANK": 267,
  "BLKA_RANK": 189,
  "PF_RANK": 127,
  "PFD_RANK": 314,
  "PTS_RANK": 334,
  "PLUS_MINUS_RANK": 144,
  "NBA_FANTASY_PTS_RANK": 328,
  "DD2_RANK": 176,
  "TD3_RANK": 20,
  "WNBA_FANTASY_PTS_RANK": 331,
  "Rookie": false
}